dolma_rust_components-1.3.0.dist-info/METADATA
dolma_rust_components-1.3.0.dist-info/WHEEL
dolma_rust_components/__init__.py
dolma_rust_components/__pycache__/__init__.cpython-312.pyc
dolma_rust_components/dolma_rust_components.cpython-312-darwin.so
dolma_rust_components/py.typed
dolma_rust_components-1.3.0.dist-info/RECORD
